vikas_pg/Engine.py
vikas_pg/__init__.py
vikas_pg/config.py
vikas_pg/crud.py
vikas_pg-0.2.1.dist-info/METADATA
vikas_pg-0.2.1.dist-info/WHEEL
vikas_pg-0.2.1.dist-info/entry_points.txt
vikas_pg-0.2.1.dist-info/top_level.txt
vikas_pg-0.2.1.dist-info/RECORD
