Metadata-Version: 2.4
Name: vikas_pg
Version: 0.2.1
Summary: High-performance PostgreSQL CRUD Operation
Home-page: https://github.com/aravindhgowham
Author: Aravindh
Author-email: aravindhvignesh58@gmail.com
Requires-Python: >=3.8,<3.14
Requires-Dist: async-lru>=2.1.0
Requires-Dist: asyncpg>=0.29.0
Requires-Dist: psycopg2-binary>=2.9.9
Requires-Dist: pydantic<3.0,>=2.7
Requires-Dist: pydantic-settings<3.0,>=2.0
Dynamic: author
Dynamic: author-email
Dynamic: description
Dynamic: description-content-type
Dynamic: home-page
Dynamic: requires-dist
Dynamic: requires-python
Dynamic: summary
